{
  "data": {
    "16278964": {
      "url": "https://raider.io/mythic-plus-runs/season-sl-2/16278964-15-plaguefall",
      "dunegonName": "Plaguefall",
      "dungeonAbbr": "PF",
      "score": 128.1,
      "keystoneLevel": 15,
      "clearTime": 1723882,
      "dateCompleted": "2021-12-29T00:35:19.000Z",
      "keyMod": 2,
      "faction": "horde",
      "partime": 2280999,
      "members": [
        "112259843",
        "187336568",
        "192926058",
        "199493521"
      ],
      "count": 4,
      "scoreColor": "#8351e8",
      "timeDiff": -557117,
      "percDiff": -0.2442425446043598
    },
    "16276245": {
      "url": "https://raider.io/mythic-plus-runs/season-sl-2/16276245-15-de-other-side",
      "dunegonName": "De Other Side",
      "dungeonAbbr": "DOS",
      "score": 127.1,
      "keystoneLevel": 15,
      "clearTime": 2156539,
      "dateCompleted": "2021-12-28T23:54:23.000Z",
      "keyMod": 1,
      "faction": "horde",
      "partime": 2580999,
      "members": [
        "112259843",
        "187336568",
        "189411814",
        "199493521"
      ],
      "count": 4,
      "scoreColor": "#7b56e7",
      "timeDiff": -424460,
      "percDiff": -0.16445570106768737
    },
    "16282026": {
      "url": "https://raider.io/mythic-plus-runs/season-sl-2/16282026-15-spires-of-ascension",
      "dunegonName": "Spires of Ascension",
      "dungeonAbbr": "SOA",
      "score": 127.6,
      "keystoneLevel": 15,
      "clearTime": 1844745,
      "dateCompleted": "2021-12-29T01:20:35.000Z",
      "keyMod": 2,
      "faction": "horde",
      "partime": 2340999,
      "members": [
        "112259843",
        "187336568",
        "198227227",
        "220581586",
        "220696506"
      ],
      "count": 5,
      "scoreColor": "#8351e8",
      "timeDiff": -496254,
      "percDiff": -0.21198385817336962
    },
    "16285081": {
      "url": "https://raider.io/mythic-plus-runs/season-sl-2/16285081-16-theater-of-pain",
      "dunegonName": "Theater of Pain",
      "dungeonAbbr": "TOP",
      "score": 130.1,
      "keystoneLevel": 16,
      "clearTime": 2264379,
      "dateCompleted": "2021-12-29T02:10:26.000Z",
      "keyMod": 1,
      "faction": "horde",
      "partime": 2280999,
      "members": [
        "187336568",
        "198377141",
        "199498006",
        "220065005"
      ],
      "count": 4,
      "scoreColor": "#8c4bea",
      "timeDiff": -16620,
      "percDiff": -0.007286281142604656
    },
    "16287540": {
      "url": "https://raider.io/mythic-plus-runs/season-sl-2/16287540-15-theater-of-pain",
      "dunegonName": "Theater of Pain",
      "dungeonAbbr": "TOP",
      "score": 127.6,
      "keystoneLevel": 15,
      "clearTime": 1811144,
      "dateCompleted": "2021-12-29T02:59:54.000Z",
      "keyMod": 2,
      "faction": "horde",
      "partime": 2280999,
      "members": [
        "112259843",
        "220581586"
      ],
      "count": 2,
      "scoreColor": "#8351e8",
      "timeDiff": -469855,
      "percDiff": -0.20598649977487937
    },
    "16355966": {
      "url": "https://raider.io/mythic-plus-runs/season-sl-2/16355966-17-halls-of-atonement",
      "dunegonName": "Halls of Atonement",
      "dungeonAbbr": "HOA",
      "score": 136.1,
      "keystoneLevel": 17,
      "clearTime": 1750065,
      "dateCompleted": "2021-12-30T02:06:11.000Z",
      "keyMod": 1,
      "faction": "horde",
      "partime": 1920999,
      "members": [
        "112259843",
        "219591485",
        "220581586"
      ],
      "count": 3,
      "scoreColor": "#a837e9",
      "timeDiff": -170934,
      "percDiff": -0.08898182664332466
    },
    "16476165": {
      "url": "https://raider.io/mythic-plus-runs/season-sl-2/16476165-15-the-necrotic-wake",
      "dunegonName": "The Necrotic Wake",
      "dungeonAbbr": "NW",
      "score": 119.9,
      "keystoneLevel": 15,
      "clearTime": 2179820,
      "dateCompleted": "2021-12-31T18:04:36.000Z",
      "keyMod": 0,
      "faction": "alliance",
      "partime": 2160999,
      "members": [
        "160713186",
        "186046561",
        "188463632",
        "188749542",
        "190679271"
      ],
      "count": 5,
      "scoreColor": "#406ae0",
      "timeDiff": 18821,
      "percDiff": 0.008709397829429921
    },
    "16476166": {
      "url": "https://raider.io/mythic-plus-runs/season-sl-2/16476166-14-theater-of-pain",
      "dunegonName": "Theater of Pain",
      "dungeonAbbr": "TOP",
      "score": 120.3,
      "keystoneLevel": 14,
      "clearTime": 2229422,
      "dateCompleted": "2021-12-31T17:21:29.000Z",
      "keyMod": 1,
      "faction": "alliance",
      "partime": 2280999,
      "members": [
        "160713186",
        "186046561",
        "188463632",
        "188749542",
        "190679271"
      ],
      "count": 5,
      "scoreColor": "#4f67e1",
      "timeDiff": -51577,
      "percDiff": -0.022611583784122646
    },
    "16706177": {
      "url": "https://raider.io/mythic-plus-runs/season-sl-2/16706177-15-theater-of-pain",
      "dunegonName": "Theater of Pain",
      "dungeonAbbr": "TOP",
      "score": 128.5,
      "keystoneLevel": 15,
      "clearTime": 1639523,
      "dateCompleted": "2022-01-04T00:43:43.000Z",
      "keyMod": 2,
      "faction": "horde",
      "partime": 2280999,
      "members": [
        "182359738",
        "183203691",
        "187336568",
        "199951572",
        "201274632"
      ],
      "count": 5,
      "scoreColor": "#8351e8",
      "timeDiff": -641476,
      "percDiff": -0.28122590145808923
    },
    "16708382": {
      "url": "https://raider.io/mythic-plus-runs/season-sl-2/16708382-15-sanguine-depths",
      "dunegonName": "Sanguine Depths",
      "dungeonAbbr": "SD",
      "score": 129,
      "keystoneLevel": 15,
      "clearTime": 1664562,
      "dateCompleted": "2022-01-04T01:22:53.000Z",
      "keyMod": 2,
      "faction": "horde",
      "partime": 2460999,
      "members": [
        "112272998",
        "187336568",
        "189081947",
        "190562532"
      ],
      "count": 4,
      "scoreColor": "#8351e8",
      "timeDiff": -796437,
      "percDiff": -0.32362345535288717
    },
    "16711332": {
      "url": "https://raider.io/mythic-plus-runs/season-sl-2/16711332-16-mists-of-tirna-scithe",
      "dunegonName": "Mists of Tirna Scithe",
      "dungeonAbbr": "MISTS",
      "score": 131.3,
      "keystoneLevel": 16,
      "clearTime": 1619888,
      "dateCompleted": "2022-01-04T02:16:06.000Z",
      "keyMod": 1,
      "faction": "alliance",
      "partime": 1800999,
      "members": [
        "159787507",
        "168845102",
        "191546276",
        "191549898",
        "191594602"
      ],
      "count": 5,
      "scoreColor": "#9445eb",
      "timeDiff": -181111,
      "percDiff": -0.10056141063931745
    },
    "16713570": {
      "url": "https://raider.io/mythic-plus-runs/season-sl-2/16713570-16-theater-of-pain",
      "dunegonName": "Theater of Pain",
      "dungeonAbbr": "TOP",
      "score": 130.9,
      "keystoneLevel": 16,
      "clearTime": 2109645,
      "dateCompleted": "2022-01-04T02:59:12.000Z",
      "keyMod": 1,
      "faction": "alliance",
      "partime": 2280999,
      "members": [
        "159787507",
        "168845102",
        "191546276",
        "191594602",
        "191665320"
      ],
      "count": 5,
      "scoreColor": "#9445eb",
      "timeDiff": -171354,
      "percDiff": -0.07512234770817527
    }
  }
}